donzo_multiple/__init__.py
donzo_multiple/cal_multiple.py
donzo_multiple-0.1.4.dist-info/METADATA
donzo_multiple-0.1.4.dist-info/WHEEL
donzo_multiple-0.1.4.dist-info/entry_points.txt
donzo_multiple-0.1.4.dist-info/top_level.txt
donzo_multiple-0.1.4.dist-info/RECORD
